odoo/addons/mgmtsystem_info_security_manual/README.rst
odoo/addons/mgmtsystem_info_security_manual/__init__.py
odoo/addons/mgmtsystem_info_security_manual/__manifest__.py
odoo/addons/mgmtsystem_info_security_manual/data/information_security_manual.xml
odoo/addons/mgmtsystem_info_security_manual/i18n/it.po
odoo/addons/mgmtsystem_info_security_manual/i18n/mgmtsystem_info_security_manual.pot
odoo/addons/mgmtsystem_info_security_manual/readme/CONTRIBUTORS.rst
odoo/addons/mgmtsystem_info_security_manual/readme/DESCRIPTION.rst
odoo/addons/mgmtsystem_info_security_manual/readme/USAGE.rst
odoo/addons/mgmtsystem_info_security_manual/static/description/icon.png
odoo/addons/mgmtsystem_info_security_manual/static/description/index.html
odoo13_addon_mgmtsystem_info_security_manual-13.0.1.0.1.dev6.dist-info/METADATA
odoo13_addon_mgmtsystem_info_security_manual-13.0.1.0.1.dev6.dist-info/WHEEL
odoo13_addon_mgmtsystem_info_security_manual-13.0.1.0.1.dev6.dist-info/top_level.txt
odoo13_addon_mgmtsystem_info_security_manual-13.0.1.0.1.dev6.dist-info/RECORD
